taobao_title_mcp/README.md
taobao_title_mcp/__init__.py
taobao_title_mcp/__main__.py
taobao_title_mcp/server.py
taobao_title_mcp/prompts/__init__.py
taobao_title_mcp/prompts/title_prompts.py
taobao_title_mcp/resources/__init__.py
taobao_title_mcp/resources/info_resources.py
taobao_title_mcp/tools/__init__.py
taobao_title_mcp/tools/title_tools.py
taobao_title_mcp-0.1.1.dist-info/METADATA
taobao_title_mcp-0.1.1.dist-info/WHEEL
taobao_title_mcp-0.1.1.dist-info/entry_points.txt
taobao_title_mcp-0.1.1.dist-info/top_level.txt
taobao_title_mcp-0.1.1.dist-info/RECORD
