Metadata-Version: 2.4
Name: taobao-title-mcp
Version: 0.1.1
Summary: 淘宝商品标题生成MCP服务器
Author-email: 三少科技 <example@example.com>
License: MIT
Project-URL: Homepage, https://github.com/yourusername/taobao-title-mcp
Project-URL: Bug Tracker, https://github.com/yourusername/taobao-title-mcp/issues
Keywords: mcp,taobao,title,generation,ai
Classifier: Programming Language :: Python :: 3
Classifier: Programming Language :: Python :: 3.8
Classifier: Programming Language :: Python :: 3.9
Classifier: Programming Language :: Python :: 3.10
Classifier: Programming Language :: Python :: 3.11
Classifier: License :: OSI Approved :: MIT License
Classifier: Operating System :: OS Independent
Classifier: Intended Audience :: Developers
Classifier: Topic :: Software Development :: Libraries :: Python Modules
Requires-Python: >=3.8
Requires-Dist: mcp>=1.6.0
Requires-Dist: requests>=2.31.0
Requires-Dist: Pillow>=10.1.0
Provides-Extra: dev
Requires-Dist: pytest>=7.0.0; extra == "dev"
Requires-Dist: black>=23.0.0; extra == "dev"
Requires-Dist: isort>=5.0.0; extra == "dev"
